turboml/__init__.py
turboml/common/__init__.py
turboml/common/api.py
turboml/common/concurrent.py
turboml/common/dataloader.py
turboml/common/datasets.py
turboml/common/default_model_configs.py
turboml/common/env.py
turboml/common/feature_engineering.py
turboml/common/internal.py
turboml/common/llm.py
turboml/common/ml_algs.py
turboml/common/model_comparison.py
turboml/common/models.py
turboml/common/namespaces.py
turboml/common/protos/__init__.py
turboml/common/protos/config_pb2.py
turboml/common/protos/config_pb2.pyi
turboml/common/protos/flink_pb2.py
turboml/common/protos/flink_pb2.pyi
turboml/common/protos/flink_pb2_grpc.py
turboml/common/protos/input_pb2.py
turboml/common/protos/input_pb2.pyi
turboml/common/protos/metrics_pb2.py
turboml/common/protos/metrics_pb2.pyi
turboml/common/protos/ml_service_pb2.py
turboml/common/protos/ml_service_pb2.pyi
turboml/common/protos/ml_service_pb2_grpc.py
turboml/common/protos/output_pb2.py
turboml/common/protos/output_pb2.pyi
turboml/common/protos/sources_pb2.py
turboml/common/protos/sources_pb2.pyi
turboml/common/pymodel.py
turboml/common/pytypes.py
turboml/common/sources/__init__.py
turboml/common/sources/sources_p2p.py
turboml/common/types.py
turboml/common/udf.py
turboml/common/util.py
turboml_sdk-0.1.6.dist-info/METADATA
turboml_sdk-0.1.6.dist-info/WHEEL
turboml_sdk-0.1.6.dist-info/RECORD
