Metadata-Version: 2.1
Name: turboml-sdk
Version: 0.1.6
Summary: Python SDK for TurboML
Author: TurboML, Inc.
Author-email: hello@turboml.com
Requires-Python: >=3.11,<3.12
Classifier: Programming Language :: Python :: 3
Classifier: Programming Language :: Python :: 3.11
Requires-Dist: cloudpickle (>=3,<4)
Requires-Dist: datafusion (>=36.0.0,<37.0.0)
Requires-Dist: duckdb (>=1.1.3,<2.0.0)
Requires-Dist: frozendict (>=2.3.10,<3.0.0)
Requires-Dist: ibis-framework (>=9.5.0,<10.0.0)
Requires-Dist: pandas (>=2.2.3,<3.0.0)
Requires-Dist: plotly (>=5.18.0,<6.0.0)
Requires-Dist: protobuf (>=5.28.3,<6.0.0)
Requires-Dist: protobuf-to-pydantic (>=0.3.0,<0.4.0)
Requires-Dist: psycopg2-binary (>=2.9.9,<3.0.0)
Requires-Dist: psycopg[binary] (>=3.1.18,<4.0.0)
Requires-Dist: psycopg_pool (>=3.2.1,<4.0.0)
Requires-Dist: pyarrow (<18.0.0)
Requires-Dist: pyarrow-hotfix (>=0.6,<0.7)
Requires-Dist: pydantic (>=2.5.3,<3.0.0)
Requires-Dist: pydantic-settings (>=2.3.4,<3.0.0)
Requires-Dist: pyjwt[crypto] (>=2.8.0,<3.0.0)
Requires-Dist: requests (>=2.31.0,<3.0.0)
Requires-Dist: risingwave (>=0.1.1,<0.2.0)
Requires-Dist: scikit-learn (>=1.5.2,<2.0.0)
Requires-Dist: tenacity (>=9.0.0,<10.0.0)
Requires-Dist: tqdm (>=4.66.5,<5.0.0)
Requires-Dist: turboml_bindings (>=0.1.0,<0.2.0)
